squircle.py
squircle-0.2.2.dist-info/LICENSE
squircle-0.2.2.dist-info/METADATA
squircle-0.2.2.dist-info/WHEEL
squircle-0.2.2.dist-info/top_level.txt
squircle-0.2.2.dist-info/RECORD
